scilint/__init__.py
scilint/_modidx.py
scilint/indicators.py
scilint/scilint.py
scilint/utils.py
scilint/experimental/__init__.py
scilint/experimental/test_nbdev.py
scilint/exploratory/__init__.py
scilint/exploratory/test_nbdev.py
scilint/test/__init__.py
scilint/test/test_nbdev.py
scilint/test/test_nbdev_high_quality.py
scilint/validated/__init__.py
scilint/validated/test_nbdev_high_quality.py
scilint-0.2.4.dist-info/LICENSE
scilint-0.2.4.dist-info/METADATA
scilint-0.2.4.dist-info/NOTICE
scilint-0.2.4.dist-info/WHEEL
scilint-0.2.4.dist-info/entry_points.txt
scilint-0.2.4.dist-info/top_level.txt
scilint-0.2.4.dist-info/RECORD
