Metadata-Version: 2.1
Name: scilint
Version: 0.2.4
Summary: infuse quality into notebook based workflows with a new type of build tool.
Home-page: https://github.com/newday-data/scilint/tree/{branch}/
Author: Donal Simmie
Author-email: oss@newday.co.uk
License: Apache Software License 2.0
Project-URL: Documentation, https://newday-data.github.io/scilint/
Keywords: research,production,exploration,CI/CD
Platform: UNKNOWN
Classifier: Development Status :: 2 - Pre-Alpha
Classifier: Intended Audience :: Science/Research
Classifier: Natural Language :: English
Classifier: Programming Language :: Python :: 3.8
Classifier: Programming Language :: Python :: 3.9
Classifier: Programming Language :: Python :: 3.10
Classifier: License :: OSI Approved :: Apache Software License
Requires-Python: >=3.8
License-File: LICENSE
License-File: NOTICE
Requires-Dist: nbdev ==2.3.12
Requires-Dist: nbformat ==5.8.0
Requires-Dist: nbqa ==1.7.0
Requires-Dist: numpy ==1.24.3
Requires-Dist: pandas ==2.0.1
Requires-Dist: tabulate ==0.8.9
Requires-Dist: black ==23.3.0
Requires-Dist: isort ==5.12.0
Requires-Dist: autoflake ==2.1.1
Provides-Extra: dev
